{
  "nom": "Corse",
  "total": 98,
  "votes": [
    {
      "key": "LASSALLE Jean",
      "value": 33,
      "rang": 1
    },
    {
      "key": "MACRON Emmanuel",
      "value": 13,
      "rang": 2
    },
    {
      "key": "JADOT Yannick",
      "value": 12,
      "rang": 3
    },
    {
      "key": "PÉCRESSE Valérie",
      "value": 11,
      "rang": 4
    },
    {
      "key": "ZEMMOUR Éric",
      "value": 8,
      "rang": 5
    },
    {
      "key": "ARTHAUD Nathalie",
      "value": 6,
      "rang": 6
    },
    {
      "key": "ROUSSEL Fabien",
      "value": 6,
      "rang": 6
    },
    {
      "key": "POUTOU Philippe",
      "value": 5,
      "rang": 8
    },
    {
      "key": "DUPONT-AIGNAN Nicolas",
      "value": 1,
      "rang": 9
    },
    {
      "key": "LE PEN Marine",
      "value": 1,
      "rang": 9
    },
    {
      "key": "MÉLENCHON Jean-Luc",
      "value": 1,
      "rang": 9
    },
    {
      "key": "THOUY Hélène",
      "value": 1,
      "rang": 9
    }
  ]
}