{
  "nom": "Ardennes",
  "total": 105,
  "votes": [
    {
      "key": "PÉCRESSE Valérie",
      "value": 23,
      "rang": 1
    },
    {
      "key": "DUPONT-AIGNAN Nicolas",
      "value": 18,
      "rang": 2
    },
    {
      "key": "ARTHAUD Nathalie",
      "value": 15,
      "rang": 3
    },
    {
      "key": "LASSALLE Jean",
      "value": 8,
      "rang": 4
    },
    {
      "key": "MACRON Emmanuel",
      "value": 7,
      "rang": 5
    },
    {
      "key": "ASSELINEAU François",
      "value": 6,
      "rang": 6
    },
    {
      "key": "ZEMMOUR Éric",
      "value": 6,
      "rang": 6
    },
    {
      "key": "KAZIB Anasse",
      "value": 4,
      "rang": 8
    },
    {
      "key": "HIDALGO Anne",
      "value": 3,
      "rang": 9
    },
    {
      "key": "LE PEN Marine",
      "value": 3,
      "rang": 9
    },
    {
      "key": "EGGER Clara",
      "value": 2,
      "rang": 11
    },
    {
      "key": "JADOT Yannick",
      "value": 2,
      "rang": 11
    },
    {
      "key": "KUZMANOVIC Georges",
      "value": 2,
      "rang": 11
    },
    {
      "key": "POUTOU Philippe",
      "value": 2,
      "rang": 11
    },
    {
      "key": "THOUY Hélène",
      "value": 2,
      "rang": 11
    },
    {
      "key": "KOENIG Gaspard",
      "value": 1,
      "rang": 16
    },
    {
      "key": "MÉLENCHON Jean-Luc",
      "value": 1,
      "rang": 16
    }
  ]
}