{
  "nom": "Essonne",
  "total": 95,
  "votes": [
    {
      "key": "PÉCRESSE Valérie",
      "value": 48,
      "rang": 1
    },
    {
      "key": "MACRON Emmanuel",
      "value": 14,
      "rang": 2
    },
    {
      "key": "JADOT Yannick",
      "value": 11,
      "rang": 3
    },
    {
      "key": "ROUSSEL Fabien",
      "value": 6,
      "rang": 4
    },
    {
      "key": "HIDALGO Anne",
      "value": 4,
      "rang": 5
    },
    {
      "key": "DUPONT-AIGNAN Nicolas",
      "value": 3,
      "rang": 6
    },
    {
      "key": "MÉLENCHON Jean-Luc",
      "value": 3,
      "rang": 6
    },
    {
      "key": "LE PEN Marine",
      "value": 2,
      "rang": 8
    },
    {
      "key": "ASSELINEAU François",
      "value": 1,
      "rang": 9
    },
    {
      "key": "KOENIG Gaspard",
      "value": 1,
      "rang": 9
    },
    {
      "key": "POUTOU Philippe",
      "value": 1,
      "rang": 9
    },
    {
      "key": "THOUY Hélène",
      "value": 1,
      "rang": 9
    }
  ]
}