{
  "nom": "Paris",
  "total": 126,
  "votes": [
    {
      "key": "HIDALGO Anne",
      "value": 57,
      "rang": 1
    },
    {
      "key": "PÉCRESSE Valérie",
      "value": 31,
      "rang": 2
    },
    {
      "key": "MACRON Emmanuel",
      "value": 14,
      "rang": 3
    },
    {
      "key": "ROUSSEL Fabien",
      "value": 11,
      "rang": 4
    },
    {
      "key": "JADOT Yannick",
      "value": 8,
      "rang": 5
    },
    {
      "key": "MÉLENCHON Jean-Luc",
      "value": 3,
      "rang": 6
    },
    {
      "key": "KOENIG Gaspard",
      "value": 1,
      "rang": 7
    },
    {
      "key": "THOUY Hélène",
      "value": 1,
      "rang": 7
    }
  ]
}